{
    "pageid": "5624",
    "title": "FT4",
    "spectrum": [
        "Ft42.png"
    ],
    "audio": [
        "FT4 2020-02-16T16 22 52Z 14080.62 usb.wav"
    ],
    "category": [
        "Amateur Radio",
        "Digital"
    ],
    "frequency": [
        {
            "value": 14080000,
            "description": ""
        },
        {
            "value": 3575000,
            "description": ""
        },
        {
            "value": 7047500,
            "description": ""
        },
        {
            "value": 10140,
            "description": ""
        },
        {
            "value": 18104000,
            "description": ""
        },
        {
            "value": 21140000,
            "description": ""
        },
        {
            "value": 24919000,
            "description": ""
        },
        {
            "value": 28180000,
            "description": ""
        },
        {
            "value": 50318000,
            "description": ""
        },
        {
            "value": 144170000,
            "description": ""
        }
    ],
    "bandwidth": [
        {
            "value": 83.3,
            "description": ""
        }
    ],
    "acf": [],
    "modulation": [
        {
            "value": "4FSK",
            "description": ""
        }
    ],
    "mode": [
        {
            "value": "USB",
            "description": ""
        }
    ],
    "location": [
        {
            "value": "Worldwide",
            "description": ""
        }
    ]
}