{
    "pageid": "2220",
    "title": "Pursuit Wireless Car Key",
    "spectrum": [
        "1995_nissan_key.jpg"
    ],
    "audio": [
        "Nissan_Wireless_Key_AM_Mode.mp3"
    ],
    "category": [
        "Utility"
    ],
    "frequency": [
        {
            "value": 301500000,
            "description": ""
        },
        {
            "value": 302500000,
            "description": ""
        },
        {
            "value": 434000000,
            "description": ""
        }
    ],
    "bandwidth": [
        {
            "value": 40000,
            "description": ""
        }
    ],
    "acf": [],
    "modulation": [
        {
            "value": "AM",
            "description": ""
        }
    ],
    "mode": [
        {
            "value": "AM",
            "description": ""
        }
    ],
    "location": [
        {
            "value": "Worldwide",
            "description": ""
        }
    ],
    "short description": "Pursuit series wireless car alarm entry key, for use on vehicles equipped with Pursuit Series Car Alarm System.",
    "description": "**Pursuit series wireless car alarm** entry key, for use on vehicles equipped with Pursuit Series Car Alarm System. The transmitting key fob's are manufactured by Nutek Corporation in Taiwan."
}