{
    "pageid": "211",
    "title": "Next Generation Digital Narrowband (NXDN)",
    "spectrum": [
        "NXDN_6.25.jpg"
    ],
    "audio": [
        "NXDN_Trunking_Channel.mp3"
    ],
    "category": [
        "Trunked Radio",
        "Digital"
    ],
    "frequency": [
        {
            "value": 136000000,
            "description": ""
        },
        {
            "value": 174000000,
            "description": ""
        },
        {
            "value": 400000000,
            "description": ""
        },
        {
            "value": 520000000,
            "description": ""
        }
    ],
    "bandwidth": [
        {
            "value": 6250,
            "description": ""
        },
        {
            "value": 12500,
            "description": ""
        }
    ],
    "acf": [
        {
            "value": "80 ms",
            "description": ""
        }
    ],
    "modulation": [
        {
            "value": "4FSK",
            "description": ""
        }
    ],
    "mode": [
        {
            "value": "NFM",
            "description": ""
        }
    ],
    "location": [
        {
            "value": "Worldwide",
            "description": ""
        }
    ]
}