{
    "pageid": "3303",
    "title": "Vietnamese Siren Jammer",
    "spectrum": [
        "Vietnamese_Siren_Jammer.PNG"
    ],
    "audio": [
        "Vietnamese_siren_jammer.wav"
    ],
    "category": [],
    "frequency": [
        {
            "value": 1000000,
            "description": ""
        },
        {
            "value": 20000000,
            "description": ""
        }
    ],
    "bandwidth": [
        {
            "value": 2700000,
            "description": ""
        }
    ],
    "acf": [],
    "modulation": [],
    "mode": [
        {
            "value": "USB",
            "description": ""
        }
    ],
    "location": [
        {
            "value": "Worldwide",
            "description": ""
        }
    ],
    "short description": "Used to interrupt AM boardcast stations such as Radio Free Asia, Radio Đáp Lời Song Núi as well as Radio Sweden.",
    "description": null
}