{
    "pageid": "6110",
    "title": "1G Advanced Mobile Phone System (AMPS)",
    "spectrum": {
        "filename": "AmpsCC.png",
        "url": "https://www.sigidwiki.com/images/6/6c/AmpsCC.png"
    },
    "audio": {
        "filename": "Amps cell broadcast decreasedVOL.wav",
        "url": "https://www.sigidwiki.com/images/c/c6/Amps_cell_broadcast_decreasedVOL.wav"
    },
    "category": [
        "Commercial",
        "Analogue",
        "Digital"
    ],
    "frequency": [
        {
            "value": 824000000,
            "description": ""
        },
        {
            "value": 894000000,
            "description": ""
        }
    ],
    "bandwidth": [
        {
            "value": 30000,
            "description": ""
        },
        {
            "value": 10000,
            "description": ""
        }
    ],
    "acf": [],
    "modulation": [
        {
            "value": "FM",
            "description": ""
        },
        {
            "value": "FSK",
            "description": ""
        }
    ],
    "mode": [
        {
            "value": "NFM",
            "description": ""
        }
    ],
    "location": [
        {
            "value": "Worldwide",
            "description": ""
        }
    ],
    "short description": "The first generation of cellular mobile telecommunications, which used analogue NFM voice.",
    "description": "The Advanced Mobile Phone System (AMPS) was developed in 1978, and released to the public in 1983 by Bell Laboratories to cater for increased demand of mobile voice services.\n\nFSK signalling was used to connect mobile customers to the base station to place voice calls, this data was transmitted at 10 kbit/s. Voice data was transmitted over NFM analog modulation. \n\nAs the number of subscribers increased, some 30 kHz analog voice channels were converted to D-AMPS channels which could service more users using TDMA, at the cost of reduced voice quality.\n\nThe technology saw use in many other countries such as Australia, Canada, New Zealand, Pakistan and Spain. However many other countries had created their own systems ( [Nordic Mobile Telephone (NMT)](https://www.sigidwiki.com/wiki/Nordic Mobile Telephone (NMT)) for example).\n\nIn the 1990s, telecommunications companies worldwide started phasing out AMPS services in favour of the improved [GSM](https://www.sigidwiki.com/wiki/GSM) standard, which provided encryption and data services."
}