{
    "pageid": "208",
    "title": "Tire Pressure Monitoring System (TPMS)",
    "spectrum": [
        "TPMS.png"
    ],
    "audio": [
        "TPMS_audio.mp3"
    ],
    "category": [
        "Utility"
    ],
    "frequency": [
        {
            "value": 315000000,
            "description": ""
        },
        {
            "value": 434000000,
            "description": ""
        }
    ],
    "bandwidth": [
        {
            "value": 100000,
            "description": ""
        }
    ],
    "acf": [
        {
            "value": "7.433ms",
            "description": ""
        }
    ],
    "modulation": [
        {
            "value": "FSK",
            "description": ""
        }
    ],
    "mode": [
        {
            "value": "AM",
            "description": ""
        }
    ],
    "location": [
        {
            "value": "Worldwide",
            "description": ""
        }
    ]
}